{"data_mtime":1779046878,"dep_lines":[4,6,7,1,1,1,33,33,31,32],"dep_prios":[5,10,5,5,30,30,25,25,25,25],"dependencies":["__future__","importlib","typing","builtins","abc","types"],"hash":"36d7de192f3f23eb0ec1f1751541c85c7c9303f78a61741db576998b90172bf6","id":"torch.onnx._internal._lazy_import","ignore_all":true,"interface_hash":"460be53441f4d30c37b469236dae66e18e90ec88a78c4479fd08b6b548b94af2","mtime":1745591023,"options":{"allow_redefinition":false,"allow_untyped_globals":false,"always_false":[],"always_true":[],"bazel":false,"check_untyped_defs":false,"disable_bytearray_promotion":false,"disable_error_code":[],"disable_memoryview_promotion":false,"disabled_error_codes":[],"disallow_any_decorated":false,"disallow_any_explicit":false,"disallow_any_expr":false,"disallow_any_generics":false,"disallow_any_unimported":false,"disallow_incomplete_defs":false,"disallow_subclassing_any":false,"disallow_untyped_calls":false,"disallow_untyped_decorators":false,"disallow_untyped_defs":false,"enable_error_code":[],"enabled_error_codes":[],"extra_checks":false,"follow_imports":"normal","follow_imports_for_stubs":false,"ignore_errors":false,"ignore_missing_imports":false,"implicit_optional":false,"implicit_reexport":true,"local_partial_types":false,"mypyc":false,"old_type_inference":false,"platform":"win32","plugins":[],"strict_concatenate":false,"strict_equality":false,"strict_optional":true,"warn_no_return":true,"warn_return_any":false,"warn_unreachable":false,"warn_unused_ignores":false},"path":"C:\\Users\\32470\\AppData\\Local\\Programs\\Python\\Python312\\Lib\\site-packages\\torch\\onnx\\_internal\\_lazy_import.py","plugin_data":null,"size":1242,"suppressed":["onnxscript._framework_apis.torch_2_6","onnxscript._framework_apis","onnx","onnxscript"],"version_id":"1.7.1"}